README.md
setup.py
hunter_pkg/__init__.py
hunter_pkg/colors.py
hunter_pkg/engine.py
hunter_pkg/event.py
hunter_pkg/flogging.py
hunter_pkg/game_map.py
hunter_pkg/input_handlers.py
hunter_pkg/log_level.py
hunter_pkg/main.py
hunter_pkg/map_generator.py
hunter_pkg/pathfinder.py
hunter_pkg/player_actions.py
hunter_pkg/renderer.py
hunter_pkg/stats.py
hunter_pkg/status_effects.py
hunter_pkg/terrain.py
hunter_pkg/vision_map.py
hunter_pkg/entities/__init__.py
hunter_pkg/entities/base_entity.py
hunter_pkg/entities/berry_bush.py
hunter_pkg/entities/bow.py
hunter_pkg/entities/camp.py
hunter_pkg/entities/deer.py
hunter_pkg/entities/entity_actions.py
hunter_pkg/entities/fog.py
hunter_pkg/entities/hunter.py
hunter_pkg/entities/maps.py
hunter_pkg/entities/rabbit.py
hunter_pkg/entities/wolf.py
hunter_pkg/helpers/__init__.py
hunter_pkg/helpers/coord.py
hunter_pkg/helpers/direction.py
hunter_pkg/helpers/generic.py
hunter_pkg/helpers/layers.py
hunter_pkg/helpers/math.py
hunter_pkg/helpers/rng.py
hunter_pkg/helpers/time_of_day.py
hunter_tdb.egg-info/PKG-INFO
hunter_tdb.egg-info/SOURCES.txt
hunter_tdb.egg-info/dependency_links.txt
hunter_tdb.egg-info/entry_points.txt
hunter_tdb.egg-info/top_level.txt
laboratory/__init__.py
laboratory/map_blit.py
laboratory/mapgen_optimization.py
laboratory/perlin_noise.py
laboratory/renderer.py
tests/__init__.py
tests/test_math.py
tests/test_perlin_noise.py
tests/test_vision_map.py