Metadata-Version: 2.1
Name: hunter-tdb
Version: 1.3
Summary: A virtual ant farm of sorts
Home-page: https://github.com/trevordbabcock/hunter/
Author: Trevor Babcock
Author-email: trevor.d.babcock@gmail.com
License: UNKNOWN
Platform: UNKNOWN
Classifier: Programming Language :: Python :: 3
Classifier: License :: OSI Approved :: GNU General Public License v3 (GPLv3)
Classifier: Operating System :: OS Independent
Classifier: Development Status :: 2 - Pre-Alpha
Classifier: Topic :: Games/Entertainment
Requires-Python: >=3.8
